watchlog/__init__.py
watchlog/watchlog.py
watchlog-0.1.2.dist-info/LICENSE
watchlog-0.1.2.dist-info/METADATA
watchlog-0.1.2.dist-info/WHEEL
watchlog-0.1.2.dist-info/entry_points.txt
watchlog-0.1.2.dist-info/RECORD
