Metadata-Version: 2.1
Name: watchlog
Version: 0.1.2
Summary: monitoring log files and sending parsed logs to a specified URL
Home-page: https://github.com/Euraxluo/watchlog
License: The MIT LICENSE
Keywords: log monitor,loguru,watchdog
Author: euraxluo
Author-email: euraxluo@outlook.com
Requires-Python: >=3.8,<4.0
Classifier: License :: Other/Proprietary License
Classifier: Programming Language :: Python :: 3
Classifier: Programming Language :: Python :: 3.8
Classifier: Programming Language :: Python :: 3.9
Classifier: Programming Language :: Python :: 3.10
Classifier: Programming Language :: Python :: 3.11
Requires-Dist: asyncio (>=3.4.3,<4.0.0)
Requires-Dist: httpx (>=0.23.3,<0.24.0)
Requires-Dist: loguru (>=0.7.0,<0.8.0)
Requires-Dist: requests (>=2.30.0,<3.0.0)
Requires-Dist: watchdog (>=3.0.0,<4.0.0)
Project-URL: Repository, https://github.com/Euraxluo/watchlog
